{
  "products": [
    {
      "product_ID": 1,
      "product_name": "Organic Apples",
      "price": 2.99,
      "tags": ["fruit", "organic"],
      "inventory": 100,
      "vendor_ID": 1
    },
    {
      "product_ID": 2,
      "product_name": "Wireless Mouse",
      "price": 19.99,
      "tags": ["electronics"],
      "inventory": 50,
      "vendor_ID": 2
    },
    {
      "product_ID": 3,
      "product_name": "Cotton T-Shirt",
      "price": 14.99,
      "tags": ["clothing"],
      "inventory": 75,
      "vendor_ID": 3
    },
    {
      "product_ID": 4,
      "product_name": "Kitchen Knife Set",
      "price": 49.99,
      "tags": ["home", "kitchen"],
      "inventory": 30,
      "vendor_ID": 4
    },
    {
      "product_ID": 5,
      "product_name": "Bestseller Novel",
      "price": 12.99,
      "tags": ["books"],
      "inventory": 200,
      "vendor_ID": 5
    },
    {
      "product_ID": 6,
      "product_name": "Bananas",
      "price": 0.99,
      "tags": ["fruit"],
      "inventory": 150,
      "vendor_ID": 1
    },
    {
      "product_ID": 7,
      "product_name": "Bluetooth Speaker",
      "price": 79.99,
      "tags": ["electronics"],
      "inventory": 40,
      "vendor_ID": 2
    },
    {
      "product_ID": 8,
      "product_name": "Jeans",
      "price": 39.99,
      "tags": ["clothing"],
      "inventory": 60,
      "vendor_ID": 3
    }
  ]
}